[
 {
   "name": "Rosato Dolce Spumante Manzoni Moscato",
   "year": "#N/A",
   "price": 76,
   "quantity": 11,
   "litres": "0,75",
   "houseId": 1,
   "slug": "rosato-dolce-spumante-manzoni-moscato-075",
   "collectionId": 4
 },
 {
   "name": "Valdobbiadene Prosecco Docg Brut Rivete",
   "year": "#N/A",
   "price": 84,
   "quantity": 60,
   "litres": "0,75",
   "houseId": 1,
   "slug": "valdobbiadene-prosecco-docg-brut-rivete-075",
   "collectionId": 4
 },
 {
   "name": "Valdobbiadene Prosecco Docg Dry Paradiso",
   "year": "#N/A",
   "price": 84,
   "quantity": 30,
   "litres": "0,75",
   "houseId": 1,
   "slug": "valdobbiadene-prosecco-docg-dry-paradiso-075",
   "collectionId": 4
 },
 {
   "name": "Valdobbiadene Prosecco Docg Extra Dry Sirocol",
   "year": "#N/A",
   "price": 84,
   "quantity": 60,
   "litres": "0,75",
   "houseId": 1,
   "slug": "valdobbiadene-prosecco-docg-extra-dry-sirocol-075",
   "collectionId": 4
 },
 {
   "name": "Valdobbiadene Prosecco Docg Rive Di Santo Stefano",
   "year": "#N/A",
   "price": 117,
   "quantity": 59,
   "litres": "0,75",
   "houseId": 1,
   "slug": "valdobbiadene-prosecco-docg-rive-di-santo-stefano-075",
   "collectionId": 4
 },
 {
   "name": "Vino Spumante Moscato Rosato Extra Brut",
   "year": "#N/A",
   "price": 76,
   "quantity": 12,
   "litres": "0,75",
   "houseId": 1,
   "slug": "vino-spumante-moscato-rosato-extra-brut-075",
   "collectionId": 4
 },
 {
   "name": "Bolgheri Vermentino 2022",
   "year": "#N/A",
   "price": 121,
   "quantity": 6,
   "litres": "0,75",
   "houseId": 6,
   "slug": "bolgheri-vermentino-2022-075",
   "collectionId": 3
 },
 {
   "name": "Bolle Di Terra Spumante Brut",
   "year": "2022",
   "price": 116,
   "quantity": 6,
   "litres": "0,75",
   "houseId": 6,
   "slug": "bolle-di-terra-spumante-brut-075",
   "collectionId": 4
 },
 {
   "name": "Bolle Di Terra Spumante Metodo Classico",
   "year": "#N/A",
   "price": 209,
   "quantity": 6,
   "litres": "0,75",
   "houseId": 6,
   "slug": "bolle-di-terra-spumante-metodo-classico-075",
   "collectionId": 4
 },
 {
   "name": "Lenaia Igt Toscana Rosso 2020",
   "year": "#N/A",
   "price": 92,
   "quantity": 17,
   "litres": "0,75",
   "houseId": 6,
   "slug": "lenaia-igt-toscana-rosso-2020-075",
   "collectionId": 2
 },
 {
   "name": "Maronea 2013 Bolgheri Superiore",
   "year": "2020",
   "price": 295,
   "quantity": 6,
   "litres": "0,75",
   "houseId": 6,
   "slug": "maronea-2013-bolgheri-superiore-075",
   "collectionId": 2
 },
 {
   "name": "Maronea 2020 Bolgheri Superiore",
   "year": "2013",
   "price": 907,
   "quantity": 2,
   "litres": "1",
   "houseId": 6,
   "slug": "maronea-2020-bolgheri-superiore-1",
   "collectionId": 2
 },
 {
   "name": "Maronea 2020 Bolgheri Superiore",
   "year": "2020",
   "price": 1915,
   "quantity": 1,
   "litres": "3",
   "houseId": 6,
   "slug": "maronea-2020-bolgheri-superiore-3",
   "collectionId": 2
 },
 {
   "name": "Maronea Doc Bolgheri Superiore Rosso 2020",
   "year": "2020",
   "price": 343,
   "quantity": 6,
   "litres": "0,75",
   "houseId": 6,
   "slug": "maronea-doc-bolgheri-superiore-rosso-2020-075",
   "collectionId": 2
 },
 {
   "name": "Moreccio 2021 Cutie Lemn",
   "year": "2020",
   "price": 1600,
   "quantity": 1,
   "litres": "6",
   "houseId": 6,
   "slug": "moreccio-2021-cutie-lemn-6",
   "collectionId": 2
 },
 {
   "name": "Moreccio 2021 Cutie Lemn",
   "year": "2021",
   "price": 422,
   "quantity": 2,
   "litres": "1,5",
   "houseId": 6,
   "slug": "moreccio-2021-cutie-lemn-15",
   "collectionId": 2
 },
 {
   "name": "Moreccio 2021 Cutie Lemn",
   "year": "2021",
   "price": 3200,
   "quantity": 1,
   "litres": "12",
   "houseId": 6,
   "slug": "moreccio-2021-cutie-lemn-12",
   "collectionId": 2
 },
 {
   "name": "Moreccio 2021 Cutie Lemn",
   "year": "2021",
   "price": 781,
   "quantity": 2,
   "litres": "3",
   "houseId": 6,
   "slug": "moreccio-2021-cutie-lemn-3",
   "collectionId": 2
 },
 {
   "name": "Mosaico 2019 Bolgheri",
   "year": "2021",
   "price": 181,
   "quantity": 6,
   "litres": "0,75",
   "houseId": 6,
   "slug": "mosaico-2019-bolgheri-075",
   "collectionId": 2
 },
 {
   "name": "Mosaico Doc Bolgheri Rosso 2021",
   "year": "2019",
   "price": 220,
   "quantity": 12,
   "litres": "0,75",
   "houseId": 6,
   "slug": "mosaico-doc-bolgheri-rosso-2021-075",
   "collectionId": 2
 },
 {
   "name": "Poggio Querciolo Igt Toscana Syrah 2019",
   "year": "2021",
   "price": 178,
   "quantity": 6,
   "litres": "0,75",
   "houseId": 6,
   "slug": "poggio-querciolo-igt-toscana-syrah-2019-075",
   "collectionId": 2
 },
 {
   "name": "Rose Di Terra Spumante Brut",
   "year": "2019",
   "price": 116,
   "quantity": 6,
   "litres": "0,75",
   "houseId": 6,
   "slug": "rose-di-terra-spumante-brut-075",
   "collectionId": 4
 },
 {
   "name": "Rosso 2016 Bolgheri Superiore Cf",
   "year": "#N/A",
   "price": 639,
   "quantity": 3,
   "litres": "0,75",
   "houseId": 6,
   "slug": "rosso-2016-bolgheri-superiore-cf-075",
   "collectionId": 2
 },
 {
   "name": "Aida Montepulciano D.O.C. 2020 Roșu",
   "year": "2016",
   "price": 76,
   "quantity": 24,
   "litres": "0,75",
   "houseId": 7,
   "slug": "aida-montepulciano-d.o.c.-2020-roșu-075",
   "collectionId": 2
 },
 {
   "name": "Aida Trebbiano D.O.C. 2022",
   "year": "2020",
   "price": 76,
   "quantity": 24,
   "litres": "0,75",
   "houseId": 7,
   "slug": "aida-trebbiano-d.o.c.-2022-075",
   "collectionId": 3
 },
 {
   "name": "Bag In Tube Spinelli/Na Montepulciano 22",
   "year": "2022",
   "price": 120,
   "quantity": 56,
   "litres": "3",
   "houseId": 7,
   "slug": "bag-in-tube-spinelli/na-montepulciano-22-3",
   "collectionId": 2
 },
 {
   "name": "Puntarosa Cerasuolo D.O.C. 2022",
   "year": "#N/A",
   "price": 84,
   "quantity": 24,
   "litres": "0,75",
   "houseId": 7,
   "slug": "puntarosa-cerasuolo-d.o.c.-2022-075",
   "collectionId": 1
 },
 {
   "name": "Santinumi Terra Dei Vestini Montepulciano D.O.C. 2016",
   "year": "2022",
   "price": 274,
   "quantity": 24,
   "litres": "0,75",
   "houseId": 7,
   "slug": "santinumi-terra-dei-vestini-montepulciano-d.o.c.-2016-075",
   "collectionId": 2
 },
 {
   "name": "Trinita' Montepulciano D.O.C. 2018",
   "year": "2016",
   "price": 151,
   "quantity": 24,
   "litres": "0,75",
   "houseId": 7,
   "slug": "trinita'-montepulciano-d.o.c.-2018-075",
   "collectionId": 2
 },
 {
   "name": "Alta Langa Docg Metodo Classico Brut",
   "year": "2018",
   "price": 233,
   "quantity": 6,
   "litres": "0,75",
   "houseId": 3,
   "slug": "alta-langa-docg-metodo-classico-brut-075",
   "collectionId": 4
 },
 {
   "name": "Barbera D'Asti 80Anni Cutie Lemn 2017",
   "year": "#N/A",
   "price": 315,
   "quantity": 2,
   "litres": "1,5",
   "houseId": 3,
   "slug": "barbera-d'asti-80anni-cutie-lemn-2017-15",
   "collectionId": 2
 },
 {
   "name": "Barbera D'Asti 80Anni 2017",
   "year": "2017",
   "price": 98,
   "quantity": 6,
   "litres": "0,75",
   "houseId": 3,
   "slug": "barbera-d'asti-80anni-2017-075",
   "collectionId": 2
 },
 {
   "name": "Barbera D'Asti 80Anni Cutie Lemn 2017",
   "year": "2017",
   "price": 769,
   "quantity": 2,
   "litres": "3",
   "houseId": 3,
   "slug": "barbera-d'asti-80anni-cutie-lemn-2017-3",
   "collectionId": 2
 },
 {
   "name": "Barolo Docg San Carlo 2015",
   "year": "2017",
   "price": 189,
   "quantity": 6,
   "litres": "0,75",
   "houseId": 3,
   "slug": "barolo-docg-san-carlo-2015-075",
   "collectionId": 2
 },
 {
   "name": "Doc/R Monferato Rosso",
   "year": "2015",
   "price": 60,
   "quantity": 6,
   "litres": "0,75",
   "houseId": 3,
   "slug": "doc/r-monferato-rosso-075",
   "collectionId": 2
 },
 {
   "name": "Doc/R Piemonte Albarossa",
   "year": "#N/A",
   "price": 63,
   "quantity": 6,
   "litres": "0,75",
   "houseId": 3,
   "slug": "doc/r-piemonte-albarossa-075",
   "collectionId": 2
 },
 {
   "name": "Docg/R Barbaresco 2014 Strade",
   "year": "#N/A",
   "price": 142,
   "quantity": 6,
   "litres": "0,75",
   "houseId": 3,
   "slug": "docg/r-barbaresco-2014-strade-075",
   "collectionId": 2
 },
 {
   "name": "Docg/R Barbera D'Asti Sup 2013 Gli Scaglioni",
   "year": "2014",
   "price": 337,
   "quantity": 6,
   "litres": "0,75",
   "houseId": 3,
   "slug": "docg/r-barbera-d'asti-sup-2013-gli-scaglioni-075",
   "collectionId": 2
 },
 {
   "name": "Monferato Bianco 2018",
   "year": "2013",
   "price": 55,
   "quantity": 6,
   "litres": "0,75",
   "houseId": 3,
   "slug": "monferato-bianco-2018-075",
   "collectionId": 2
 },
 {
   "name": "Negroamaro Salento Igt",
   "year": "2018",
   "price": 71,
   "quantity": 12,
   "litres": "0,75",
   "houseId": 2,
   "slug": "negroamaro-salento-igt-075",
   "collectionId": 2
 },
 {
   "name": "Nero Di Troia Puglia Igt 2019",
   "year": "#N/A",
   "price": 73,
   "quantity": 6,
   "litres": "0,75",
   "houseId": 2,
   "slug": "nero-di-troia-puglia-igt-2019-075",
   "collectionId": 2
 },
 {
   "name": "Primitivo Salento Igt",
   "year": "2019",
   "price": 78,
   "quantity": 6,
   "litres": "0,75",
   "houseId": 2,
   "slug": "primitivo-salento-igt-075",
   "collectionId": 2
 },
 {
   "name": "Susumaniello Igt 2019",
   "year": "#N/A",
   "price": 84,
   "quantity": 12,
   "litres": "0,75",
   "houseId": 2,
   "slug": "susumaniello-igt-2019-075",
   "collectionId": 2
 },
 {
   "name": "2015 3 Litri Cutie Lemn",
   "year": "2019",
   "price": 1328,
   "quantity": 2,
   "litres": "3",
   "houseId": 8,
   "slug": "2015-3-litri-cutie-lemn-3",
   "collectionId": 2
 },
 {
   "name": "5 Vite Rosso Puglia Igt 2021 15%",
   "year": "2015",
   "price": 58,
   "quantity": 6,
   "litres": "0,75",
   "houseId": 8,
   "slug": "5-vite-rosso-puglia-igt-2021-15%-075",
   "collectionId": 2
 },
 {
   "name": "Fino Puglia Igt 2022 13% Bio Floreti",
   "year": "2021",
   "price": 46,
   "quantity": 66,
   "litres": "0,75",
   "houseId": 8,
   "slug": "fino-puglia-igt-2022-13%-bio-floreti-075",
   "collectionId": 3
 },
 {
   "name": "Negroamaro Puglia Igt 2021 Passito 17,5%",
   "year": "2022",
   "price": 180,
   "quantity": 6,
   "litres": "0,75",
   "houseId": 8,
   "slug": "negroamaro-puglia-igt-2021-passito-17,5%-075",
   "collectionId": 2
 },
 {
   "name": "Pinot Griggio Delle Venezie Doc",
   "year": "2021",
   "price": 32,
   "quantity": 30,
   "litres": "0,75",
   "houseId": 8,
   "slug": "pinot-griggio-delle-venezie-doc-075",
   "collectionId": 3
 },
 {
   "name": "Primitivo Salento Igt Leggendario 2017",
   "year": "#N/A",
   "price": 181,
   "quantity": 6,
   "litres": "0,75",
   "houseId": 8,
   "slug": "primitivo-salento-igt-leggendario-2017-075",
   "collectionId": 2
 },
 {
   "name": "Verdeca 2021",
   "year": "2017",
   "price": 30,
   "quantity": 12,
   "litres": "0,75",
   "houseId": 8,
   "slug": "verdeca-2021-075",
   "collectionId": 3
 },
 {
   "name": "Vs Negroamaro Salento Igt 2018",
   "year": "2021",
   "price": 31,
   "quantity": 12,
   "litres": "0,75",
   "houseId": 8,
   "slug": "vs-negroamaro-salento-igt-2018-075",
   "collectionId": 2
 },
 {
   "name": "Vs Rosso Salento Igt 2015",
   "year": "2018",
   "price": 210,
   "quantity": 6,
   "litres": "0,75",
   "houseId": 8,
   "slug": "vs-rosso-salento-igt-2015-075",
   "collectionId": 2
 },
 {
   "name": "Cesanese Del Piglio Docg 2021",
   "year": "2015",
   "price": 115,
   "quantity": 17,
   "litres": "0,75",
   "houseId": 9,
   "slug": "cesanese-del-piglio-docg-2021-075",
   "collectionId": 2
 },
 {
   "name": "Chardonay Lazio Igt 2021",
   "year": "2021",
   "price": 83,
   "quantity": 12,
   "litres": "0,75",
   "houseId": 9,
   "slug": "chardonay-lazio-igt-2021-075",
   "collectionId": 3
 },
 {
   "name": "Frascatti Superiore Docg 2021",
   "year": "2021",
   "price": 67,
   "quantity": 18,
   "litres": "0,75",
   "houseId": 9,
   "slug": "frascatti-superiore-docg-2021-075",
   "collectionId": 3
 },
 {
   "name": "Malvasia Lazio Igt Friccicore 2021",
   "year": "2021",
   "price": 55,
   "quantity": 6,
   "litres": "0,75",
   "houseId": 9,
   "slug": "malvasia-lazio-igt-friccicore-2021-075",
   "collectionId": 3
 },
 {
   "name": "Petit Verdot Lazio 2019",
   "year": "2021",
   "price": 83,
   "quantity": 17,
   "litres": "0,75",
   "houseId": 9,
   "slug": "petit-verdot-lazio-2019-075",
   "collectionId": 2
 },
 {
   "name": "Petit Verdot Lazio Igt 2019",
   "year": "2019",
   "price": 92,
   "quantity": 6,
   "litres": "0,75",
   "houseId": 9,
   "slug": "petit-verdot-lazio-igt-2019-075",
   "collectionId": 2
 },
 {
   "name": "Roma Doc Malvasia Puntinata 2021",
   "year": "2019",
   "price": 66,
   "quantity": 30,
   "litres": "0,75",
   "houseId": 9,
   "slug": "roma-doc-malvasia-puntinata-2021-075",
   "collectionId": 3
 },
 {
   "name": "Roma Doc Rosso 2020",
   "year": "2021",
   "price": 66,
   "quantity": 17,
   "litres": "0,75",
   "houseId": 9,
   "slug": "roma-doc-rosso-2020-075",
   "collectionId": 2
 },
 {
   "name": "Sauvignon Lazio Igt 2021",
   "year": "2020",
   "price": 83,
   "quantity": 12,
   "litres": "0,75",
   "houseId": 9,
   "slug": "sauvignon-lazio-igt-2021-075",
   "collectionId": 3
 },
 {
   "name": "Syrah Lazio Igt 2019",
   "year": "2021",
   "price": 83,
   "quantity": 12,
   "litres": "0,75",
   "houseId": 9,
   "slug": "syrah-lazio-igt-2019-075",
   "collectionId": 2
 }
]